{"featureCount":1592,"formatVersion":1,"histograms":{"meta":[{"arrayParams":{"chunkSize":10000,"length":333,"urlTemplate":"hist-100000-{Chunk}.json"},"basesPerBin":"100000"},{"arrayParams":{"chunkSize":10000,"length":167,"urlTemplate":"hist-200000-{Chunk}.json"},"basesPerBin":"200000"},{"arrayParams":{"chunkSize":10000,"length":67,"urlTemplate":"hist-500000-{Chunk}.json"},"basesPerBin":"500000"}],"stats":[{"basesPerBin":"100000","max":40,"mean":4.78978978978979},{"basesPerBin":"200000","max":51,"mean":9.53892215568862},{"basesPerBin":"500000","max":73,"mean":23.7611940298507}]},"intervals":{"classes":[{"attributes":["Start","End","Strand","Name","Seq_id"],"isArrayAttr":{}},{"attributes":["Start","End","Chunk"],"isArrayAttr":{"Sublist":1}}],"count":1592,"lazyClass":1,"maxEnd":33206835,"minStart":190222,"nclist":[[1,190222,22984990,1],[1,22985082,33206835,2]],"urlTemplate":"lf-{Chunk}.json"}}